dataset_viber-0.3.1.dist-info/METADATA
dataset_viber-0.3.1.dist-info/WHEEL
dataset_viber-0.3.1.dist-info/licenses/LICENSE
dataset_viber-0.3.1.dist-info/licenses/LICENSE_HEADER
dataset_viber/__init__.py
dataset_viber/_constants.py
dataset_viber/_gradio/__init__.py
dataset_viber/_gradio/_flagging.py
dataset_viber/_gradio/_mixins/_argilla.py
dataset_viber/_gradio/_mixins/_import_export.py
dataset_viber/_gradio/_mixins/_task_config.py
dataset_viber/_gradio/annotator.py
dataset_viber/_gradio/collector.py
dataset_viber/_utils.py
dataset_viber/bulk.py
dataset_viber/examples/fn_model.py
dataset_viber/examples/fn_next_input_chat_preference.py
dataset_viber/examples/fn_next_input_image_preference.py
dataset_viber/examples/fn_next_input_synthesizer.py
dataset_viber/examples/fn_next_input_synthesizer_distilabel.py
dataset_viber/examples/interactive_components.py
dataset_viber/examples/log_to_csv.py
dataset_viber/examples/log_to_hub.py
dataset_viber/synthesizer.py
dataset_viber-0.3.1.dist-info/RECORD
