Metadata-Version: 2.1
Name: dataset-viber
Version: 0.3.1
Summary: Dataset Viber is your chill repo for data collection, annotation and vibe checks.
Author-Email: davidberenstein1957 <david.m.berenstein@gmail.com>
License: Apache 2.0
Requires-Python: <3.13,>=3.9
Requires-Dist: gradio[oauth]<5,>=4.38
Requires-Dist: datasets<3,>=2
Requires-Dist: argilla<3,>=2
Requires-Dist: gradio-huggingfacehub-search>=0.0.7
Requires-Dist: fast-sentence-transformers[gpu]>=0.5; extra == "bulk"
Requires-Dist: tabulate>=0.9.0; extra == "bulk"
Requires-Dist: umap-learn<1,>=0.5; extra == "bulk"
Requires-Dist: plotly<6,>=5; extra == "bulk"
Requires-Dist: dash<3,>=2.11; extra == "bulk"
Requires-Dist: dash-bootstrap-components>=1.6.0; extra == "bulk"
Requires-Dist: distilabel[hf-inference-endpoints]>=1.3.2; extra == "synthesizer"
Provides-Extra: bulk
Provides-Extra: synthesizer
